event2vector/__init__.py
event2vector/data.py
event2vector/models.py
event2vector-0.1.2.dist-info/METADATA
event2vector-0.1.2.dist-info/WHEEL
event2vector-0.1.2.dist-info/top_level.txt
event2vector-0.1.2.dist-info/RECORD
