Metadata-Version: 2.4
Name: event2vector
Version: 0.1.2
Summary: Scikit-learn-style geometric embeddings for event sequences.
Author: Antonin Sulc
License-Expression: MIT
Project-URL: Homepage, https://github.com/sulcantonin/event2vector
Project-URL: Repository, https://github.com/sulcantonin/event2vector
Project-URL: Issues, https://github.com/sulcantonin/event2vector/issues
Keywords: sequence-embedding,event-sequences,representation-learning,word2vec,scikit-learn,time-series
Classifier: Programming Language :: Python :: 3
Classifier: Operating System :: OS Independent
Classifier: Topic :: Scientific/Engineering :: Artificial Intelligence
Classifier: Intended Audience :: Science/Research
Requires-Python: >=3.6
Requires-Dist: numpy
Requires-Dist: torch
Requires-Dist: scikit-learn
Requires-Dist: tqdm
Provides-Extra: viz
Requires-Dist: matplotlib; extra == "viz"
Requires-Dist: seaborn; extra == "viz"
Provides-Extra: manifold
Requires-Dist: openTSNE; extra == "manifold"
Provides-Extra: nlp
Requires-Dist: gensim; extra == "nlp"
Provides-Extra: dev
Requires-Dist: pytest; extra == "dev"
Requires-Dist: black; extra == "dev"
Requires-Dist: ruff; extra == "dev"
